brainreg_napari/__init__.py
brainreg_napari/napari.yaml
brainreg_napari/register.py
brainreg_napari/sample_data.py
brainreg_napari/util.py
brainreg_napari/tests/__init__.py
brainreg_napari/tests/test_brainreg_napari.py
brainreg_napari-0.1.4.dist-info/LICENSE
brainreg_napari-0.1.4.dist-info/METADATA
brainreg_napari-0.1.4.dist-info/WHEEL
brainreg_napari-0.1.4.dist-info/entry_points.txt
brainreg_napari-0.1.4.dist-info/top_level.txt
brainreg_napari-0.1.4.dist-info/RECORD
