Metadata-Version: 2.1
Name: brainreg-napari
Version: 0.1.4
Summary: Multi-atlas whole-brain microscopy registration
Author-email: "Adam Tyson, Stephen Lenzi" <code@adamltyson.com>
License: BSD-3-Clause
Project-URL: homepage, https://brainglobe.info
Project-URL: bug_tracker, https://github.com/brainglobe/brainreg-napari/issues
Project-URL: documentation, https://docs.brainglobe.info/brainreg-napari
Project-URL: source_code, https://github.com/brainglobe/brainreg-napari
Project-URL: user_support, https://forum.image.sc/tag/brainglobe
Project-URL: twitter, https://twitter.com/brain_globe
Classifier: Development Status :: 4 - Beta
Classifier: Topic :: Scientific/Engineering :: Image Recognition
Classifier: Intended Audience :: Developers
Classifier: Intended Audience :: Science/Research
Classifier: Programming Language :: Python
Classifier: Programming Language :: Python :: 3
Classifier: Programming Language :: Python :: 3.9
Classifier: Programming Language :: Python :: 3.10
Classifier: Programming Language :: Python :: 3.11
Classifier: Operating System :: OS Independent
Requires-Python: >=3.9.0
License-File: LICENSE
Requires-Dist: napari
Requires-Dist: napari-plugin-engine >=0.1.4
Requires-Dist: magicgui
Requires-Dist: qtpy
Requires-Dist: brainglobe-napari-io <1
Requires-Dist: brainreg <1
Requires-Dist: brainreg-segment <1
Requires-Dist: brainglobe-utils <1
Requires-Dist: pooch >1
Provides-Extra: dev
Requires-Dist: check-manifest ; extra == 'dev'
Requires-Dist: gitpython ; extra == 'dev'
Requires-Dist: napari[pyqt5] ; extra == 'dev'
Requires-Dist: pre-commit ; extra == 'dev'
Requires-Dist: pytest ; extra == 'dev'
Requires-Dist: pytest-cov ; extra == 'dev'
Requires-Dist: pytest-qt ; extra == 'dev'
Requires-Dist: setuptools-scm ; extra == 'dev'
Requires-Dist: tox ; extra == 'dev'
